pypitoken/__init__.py
pypitoken/exceptions.py
pypitoken/restrictions.py
pypitoken/token.py
pypitoken-7.1.1.dist-info/METADATA
pypitoken-7.1.1.dist-info/WHEEL
pypitoken-7.1.1.dist-info/licenses/LICENSE
pypitoken-7.1.1.dist-info/RECORD
