Metadata-Version: 2.4
Name: pypitoken
Version: 7.1.1
Summary: Manipulate PyPI API tokens
Project-URL: Homepage, https://pypitoken.readthedocs.io/en/latest/
Project-URL: Repository, https://github.com/ewjoachim/pypitoken
Project-URL: Documentation, https://pypitoken.readthedocs.io/en/latest/
Author-email: Joachim Jablon <ewjoachim@gmail.com>
License-Expression: MIT
License-File: LICENSE
Keywords: api,packaging,pypi,security,token
Classifier: Programming Language :: Python :: 3.9
Classifier: Programming Language :: Python :: 3.10
Classifier: Programming Language :: Python :: 3.11
Classifier: Programming Language :: Python :: 3.12
Classifier: Programming Language :: Python :: 3.13
Classifier: Topic :: Security
Classifier: Topic :: System :: Archiving :: Packaging
Classifier: Typing :: Typed
Requires-Python: >=3.9
Requires-Dist: jsonschema
Requires-Dist: pymacaroons>=0.13.0
Requires-Dist: typing-extensions
